<!-- RICERCA RICETTE SISTEMA TS -->
<!-- HTTP Status: 500 -->
<!-- Timestamp: 2025-09-16T22:48:44.654687 -->
<!-- Endpoint: https://ricettabiancaservicetest.sanita.finanze.it/RicettaBiancaDemPrescrittoServicesWeb/services/demVisualizzaPrescrittoRicettaBianca -->
<!-- CF Medico: PROVAX00X00X000Y -->
<!-- CF Assistito: TIZIO CAIO -->
<!-- NRE: P00000000028 -->
<!-- Ambiente: produzione -->

<?xml version="1.0" encoding="UTF-8"?>

<env:Envelope xmlns:wsrf-r="http://docs.oasis-open.org/wsrf/r-2" xmlns:wsrf-bf="http://docs.oasis-open.org/wsrf/bf-2" xmlns:wsa="http://www.w3.org/2005/08/addressing" xmlns:env="http://schemas.xmlsoap.org/soap/envelope/">
<env:Header>
<wsa:To>http://www.w3.org/2005/08/addressing/anonymous</wsa:To>
<wsa:Action>http://www.w3.org/2005/08/addressing/soap/fault</wsa:Action>
<wsa:MessageID>urn:uuid:f39405a5-f2e5-4429-9b18-403d3743be4e</wsa:MessageID>
<wsa:RelatesTo/></env:Header>
<env:Body>
<env:Fault>
<faultcode>env:Client</faultcode>
<faultstring>General Failure</faultstring>
<detail>
<wsrf-r:ResourceUnknownFault>
<wsrf-bf:Timestamp>2025-09-16T20:48:44.483Z</wsrf-bf:Timestamp>
<wsrf-bf:Description>Internal Server Error</wsrf-bf:Description></wsrf-r:ResourceUnknownFault></detail></env:Fault></env:Body></env:Envelope>